setup.py
groove_waveform.egg-info/PKG-INFO
groove_waveform.egg-info/SOURCES.txt
groove_waveform.egg-info/dependency_links.txt
groove_waveform.egg-info/top_level.txt
waveform/__init__.py
waveform/waveform.cpython-36m-x86_64-linux-gnu.so
waveform/waveform.py