Metadata-Version: 1.0
Name: groove-waveform
Version: 1.1
Summary: waveform generation using libgroove
Home-page: https://github.com/geek96/waveform-python
Author: Basit Raza
Author-email: basit.raza11@gmail.com
License: UNKNOWN
Platform: UNKNOWN
